silberstral/__init__.py
silberstral/silberstral.py
silberstral-0.2.3.dist-info/LICENSE.txt
silberstral-0.2.3.dist-info/METADATA
silberstral-0.2.3.dist-info/WHEEL
silberstral-0.2.3.dist-info/top_level.txt
silberstral-0.2.3.dist-info/RECORD
