Metadata-Version: 2.1
Name: silberstral
Version: 0.2.3
Summary: Reveals the true shape of type vars
Home-page: https://github.com/tobias-kirschstein/silberstral
Author: Tobias Kirschstein
Author-email: tobias.kirschstein@gmail.com
License: MIT
Keywords: typing,type var,instantiation,generics
Classifier: Development Status :: 4 - Beta
Classifier: Intended Audience :: Developers
Classifier: Topic :: Software Development :: Build Tools
Classifier: Programming Language :: Python :: 3.7
Classifier: Programming Language :: Python :: 3.8
Classifier: Programming Language :: Python :: 3.9
Classifier: Programming Language :: Python :: 3.10
Classifier: Operating System :: OS Independent
Classifier: License :: OSI Approved :: MIT License
Requires-Python: >=3.7
License-File: LICENSE.txt
Requires-Dist: dacite (<=1.7.0,>=1.6.0)
